grpc_helpers/__init__.py
grpc_helpers/importer.py
grpc_helpers/proxy.py
grpc_helpers/server.py
grpcio_helpers-0.0.9.dist-info/LICENSE
grpcio_helpers-0.0.9.dist-info/METADATA
grpcio_helpers-0.0.9.dist-info/WHEEL
grpcio_helpers-0.0.9.dist-info/top_level.txt
grpcio_helpers-0.0.9.dist-info/RECORD
