Metadata-Version: 2.1
Name: grpcio-helpers
Version: 0.0.9
Summary: Helper tools for importing and serving gRPC services
Home-page: https://github.com/KnowitSolutions/grpcio-helpers
Author: Andreas Hagen
Author-email: a.hagen@knowit.no
License: MIT
Platform: UNKNOWN
Classifier: Programming Language :: Python :: 3
Classifier: License :: OSI Approved :: MIT License
Classifier: Operating System :: OS Independent
Requires-Dist: grpcio
Requires-Dist: grpcio-tools
Provides-Extra: proxy
Requires-Dist: quart ; extra == 'proxy'
Provides-Extra: well-known-protos
Requires-Dist: googleapis-common-protos ; extra == 'well-known-protos'
